odoo/addons/cooperator_subscription_form_with_iban/README.md
odoo/addons/cooperator_subscription_form_with_iban/__init__.py
odoo/addons/cooperator_subscription_form_with_iban/__manifest__.py
odoo/addons/cooperator_subscription_form_with_iban/views/subscription_template.xml
odoo12_addon_cooperator_subscription_form_with_iban-12.0.1.0.0.dist-info/METADATA
odoo12_addon_cooperator_subscription_form_with_iban-12.0.1.0.0.dist-info/WHEEL
odoo12_addon_cooperator_subscription_form_with_iban-12.0.1.0.0.dist-info/top_level.txt
odoo12_addon_cooperator_subscription_form_with_iban-12.0.1.0.0.dist-info/RECORD
